{
  "config_name": "alpha_0.05",
  "history": [
    {
      "trained_episodes": 0,
      "seed_means": [
        -99.89999999999856,
        -99.89999999999856,
        -99.89999999999856
      ],
      "seed_success": [
        0.0,
        0.0,
        0.0
      ],
      "mean": -99.89999999999856,
      "std": 0.0,
      "min": -99.89999999999856,
      "max": -99.89999999999856,
      "p25": -99.89999999999856,
      "p50": -99.89999999999856,
      "p75": -99.89999999999856,
      "success_rate": 0.0,
      "success_std": 0.0,
      "mean_steps": 999.0,
      "n_seeds": 3
    },
    {
      "trained_episodes": 1000,
      "seed_means": [
        0.0,
        0.0,
        0.0
      ],
      "seed_success": [
        0.0,
        0.0,
        0.0
      ],
      "mean": 0.0,
      "std": 0.0,
      "min": 0.0,
      "max": 0.0,
      "p25": 0.0,
      "p50": 0.0,
      "p75": 0.0,
      "success_rate": 0.0,
      "success_std": 0.0,
      "mean_steps": 999.0,
      "n_seeds": 3
    },
    {
      "trained_episodes": 2000,
      "seed_means": [
        0.0,
        0.0,
        0.0
      ],
      "seed_success": [
        0.0,
        0.0,
        0.0
      ],
      "mean": 0.0,
      "std": 0.0,
      "min": 0.0,
      "max": 0.0,
      "p25": 0.0,
      "p50": 0.0,
      "p75": 0.0,
      "success_rate": 0.0,
      "success_std": 0.0,
      "mean_steps": 999.0,
      "n_seeds": 3
    },
    {
      "trained_episodes": 3000,
      "seed_means": [
        34.827000000000005,
        91.89800000000001,
        92.193
      ],
      "seed_success": [
        0.37,
        0.99,
        1.0
      ],
      "mean": 72.97266666666667,
      "std": 26.973328435491396,
      "min": 34.827000000000005,
      "max": 92.193,
      "p25": 63.36250000000001,
      "p50": 91.89800000000001,
      "p75": 92.0455,
      "success_rate": 0.7866666666666666,
      "success_std": 0.29465610840812756,
      "mean_steps": 326.46,
      "n_seeds": 3
    },
    {
      "trained_episodes": 4000,
      "seed_means": [
        91.028,
        89.79800000000003,
        90.48100000000004
      ],
      "seed_success": [
        0.99,
        0.99,
        1.0
      ],
      "mean": 90.43566666666669,
      "std": 0.5031675223576598,
      "min": 89.79800000000003,
      "max": 91.028,
      "p25": 90.13950000000003,
      "p50": 90.48100000000004,
      "p75": 90.75450000000002,
      "success_rate": 0.9933333333333333,
      "success_std": 0.004714045207910321,
      "mean_steps": 126.85000000000001,
      "n_seeds": 3
    },
    {
      "trained_episodes": 5000,
      "seed_means": [
        -91.52099999999906,
        89.73100000000004,
        92.84400000000004
      ],
      "seed_success": [
        0.0,
        0.99,
        1.0
      ],
      "mean": 30.35133333333367,
      "std": 86.18612384962064,
      "min": -91.52099999999906,
      "max": 92.84400000000004,
      "p25": -0.8949999999995129,
      "p50": 89.73100000000004,
      "p75": 91.28750000000004,
      "success_rate": 0.6633333333333333,
      "success_std": 0.46906526435265083,
      "mean_steps": 409.92,
      "n_seeds": 3
    },
    {
      "trained_episodes": 6000,
      "seed_means": [
        88.91900000000004,
        89.69900000000003,
        87.45900000000007
      ],
      "seed_success": [
        1.0,
        1.0,
        0.99
      ],
      "mean": 88.69233333333337,
      "std": 0.9284156157430347,
      "min": 87.45900000000007,
      "max": 89.69900000000003,
      "p25": 88.18900000000005,
      "p50": 88.91900000000004,
      "p75": 89.30900000000003,
      "success_rate": 0.9966666666666667,
      "success_std": 0.004714045207910321,
      "mean_steps": 145.29,
      "n_seeds": 3
    },
    {
      "trained_episodes": 7000,
      "seed_means": [
        88.60700000000004,
        91.891,
        93.374
      ],
      "seed_success": [
        0.99,
        1.0,
        1.0
      ],
      "mean": 91.2906666666667,
      "std": 1.9918789008259203,
      "min": 88.60700000000004,
      "max": 93.374,
      "p25": 90.24900000000002,
      "p50": 91.891,
      "p75": 92.6325,
      "success_rate": 0.9966666666666667,
      "success_std": 0.004714045207910321,
      "mean_steps": 136.02,
      "n_seeds": 3
    },
    {
      "trained_episodes": 8000,
      "seed_means": [
        93.42200000000001,
        93.05800000000004,
        -90.8679999999991
      ],
      "seed_success": [
        1.0,
        1.0,
        0.0
      ],
      "mean": 31.87066666666698,
      "std": 86.78947073362154,
      "min": -90.8679999999991,
      "max": 93.42200000000001,
      "p25": 1.0950000000004678,
      "p50": 93.05800000000004,
      "p75": 93.24000000000002,
      "success_rate": 0.6666666666666666,
      "success_std": 0.4714045207910317,
      "mean_steps": 392.6433333333334,
      "n_seeds": 3
    },
    {
      "trained_episodes": 9000,
      "seed_means": [
        93.62500000000001,
        92.42500000000001,
        92.28400000000002
      ],
      "seed_success": [
        1.0,
        0.99,
        0.99
      ],
      "mean": 92.77800000000002,
      "std": 0.6016793165798527,
      "min": 92.28400000000002,
      "max": 93.62500000000001,
      "p25": 92.35450000000002,
      "p50": 92.42500000000001,
      "p75": 93.025,
      "success_rate": 0.9933333333333333,
      "success_std": 0.004714045207910321,
      "mean_steps": 104.53333333333335,
      "n_seeds": 3
    },
    {
      "trained_episodes": 10000,
      "seed_means": [
        91.05900000000003,
        91.179,
        92.947
      ],
      "seed_success": [
        0.99,
        0.99,
        0.99
      ],
      "mean": 91.72833333333335,
      "std": 0.8631188922866954,
      "min": 91.05900000000003,
      "max": 92.947,
      "p25": 91.11900000000001,
      "p50": 91.179,
      "p75": 92.063,
      "success_rate": 0.9899999999999999,
      "success_std": 1.1102230246251565e-16,
      "mean_steps": 104.00999999999999,
      "n_seeds": 3
    }
  ],
  "seeds": [
    0,
    1,
    2
  ],
  "multiseed": true
}